LICENSE
README.md
md5ct.py
setup.py
md5ct.egg-info/PKG-INFO
md5ct.egg-info/SOURCES.txt
md5ct.egg-info/dependency_links.txt
md5ct.egg-info/entry_points.txt
md5ct.egg-info/top_level.txt