Metadata-Version: 2.1
Name: md5ct
Version: 0.1.8
Summary: a md5 batch change tool
Home-page: https://github.com/ixiongyu/md5changer
Author: xiongyu
Author-email: ixiongyu@gmail.com
License: UNKNOWN
Keywords: MD5
Platform: UNKNOWN
Classifier: Programming Language :: Python :: 3
Classifier: License :: OSI Approved :: MIT License
Classifier: Operating System :: OS Independent
Requires-Python: >=3.6
License-File: LICENSE
